<?xml version = '1.0' encoding = 'UTF-8'?>
<Relation class="oracle.dbtools.crest.model.design.logical.Relation" name="ORDERS_SALES_REP_FK" id="E30BC26B-4656-AD91-150F-66CD9380B1D6" directorySegmentName="seg_0">
   <createdBy>Administrator</createdBy>
   <createdTime>2008-11-18 12:15:36 UTC</createdTime>
   <changedBy>smharper</changedBy>
   <changedTime>2009-01-30 17:20:05 UTC</changedTime>
   <generatorID>0E02678F-6B1A-2259-CC3D-EFA0FB7B4690</generatorID>
   <ownerDesignName>all_schemas</ownerDesignName>
   <identifying>false</identifying>
   <optionalSource>true</optionalSource>
   <optionalTarget>true</optionalTarget>
   <sourceCardinality>1</sourceCardinality>
   <sourceEntity>EEE3ABF9-1CE1-846A-4FBA-81621407E503</sourceEntity>
   <targetCardinalityString>*</targetCardinalityString>
   <targetEntity>AF51C786-B84D-BA70-5A4C-95CA1A3963F6</targetEntity>
   <transferable>true</transferable>
</Relation>